{
  "schema_version": "scryer.plugin.child_catalog.v2",
  "id": "torznab",
  "name": "Torznab Indexer",
  "description": "Generic Torznab-compatible torrent indexer for Jackett, Prowlarr, and native Torznab feeds",
  "plugin_type": "torrent_indexer",
  "provider_type": "torznab",
  "publisher": "scryer",
  "support_tier": "official",
  "docs_url": "https://github.com/scryer-media/scryer-plugins/tree/main/torznab",
  "source_repo": "https://github.com/scryer-media/scryer-plugins/tree/main/torznab",
  "releases": [
    {
      "version": "0.1.2",
      "sdk_constraint": ">=1.3.0, <1.4.0",
      "artifact_manifest_url": "https://github.com/scryer-media/scryer-plugins/releases/download/plugins%2Ftorznab%2Fv0.1.2/plugin.manifest.json"
    },
    {
      "version": "0.1.3",
      "sdk_constraint": ">=1.4.0, <1.5.0",
      "artifact_manifest_url": "https://github.com/scryer-media/scryer-plugins/releases/download/plugins%2Ftorznab%2Fv0.1.3/plugin.manifest.json"
    },
    {
      "version": "0.1.4",
      "sdk_constraint": ">=1.0.0, <1.1.0",
      "artifact_manifest_url": "https://github.com/scryer-media/scryer-plugins/releases/download/plugins%2Ftorznab%2Fv0.1.4/plugin.manifest.json"
    }
  ]
}
